hellomood/LoadPage.py
hellomood/MoodAnalyzerGUI.py
hellomood/PlaylistGUI.py
hellomood/PlaylistGenerator.py
hellomood/SpotifyAuthorization.py
hellomood/Spotipy.py
hellomood/UserLogin.py
hellomood/UserSummary.py
hellomood/__init__.py
hellomood/emotions.txt
hellomood/main.py
hellomood/moodAnalyzer.py
hellomood/moodTrendsPg.py
hellomood/imgs/arrow.png
hellomood/imgs/awful.jpeg
hellomood/imgs/bad.jpeg
hellomood/imgs/excited.jpeg
hellomood/imgs/happy.jpeg
hellomood/imgs/love.jpeg
hellomood/imgs/okay.jpeg
hellomood-0.108.dist-info/LICENSE
hellomood-0.108.dist-info/METADATA
hellomood-0.108.dist-info/WHEEL
hellomood-0.108.dist-info/entry_points.txt
hellomood-0.108.dist-info/top_level.txt
hellomood-0.108.dist-info/RECORD
