Metadata-Version: 2.1
Name: hellomood
Version: 0.108
Summary: use sentiment analysis to create a playlist that matches someone's mood and also predict songs to rise in popularity.
Home-page: https://github.com/dianas11xx/MoodipyTest
Author: Noteworthy
Author-email: UNKNOWN
License: GPL 3
Platform: UNKNOWN
Requires-Dist: PyQt5-sip (>=4.19.19)
Requires-Dist: PyQt5 (>=5.12)
Requires-Dist: nltk (==3.6.2)
Requires-Dist: requests (>=2.25.0)
Requires-Dist: screeninfo (==0.6.7)
Requires-Dist: spotipy (==2.18.0)
Requires-Dist: urllib3 (>=1.26.0)
